Classfile /D:/优秀源码/dataTodata/test/target/classes/com/gaga/byteCode/HelloWordByteCode.class
  Last modified 2021-1-28; size 704 bytes
  MD5 checksum 7a8fb82428d9576f70a0a6106a39d8df
  Compiled from "HelloWordByteCode.java"
public class com.gaga.byteCode.HelloWordByteCode
  minor version: 0
  major version: 52
  flags: ACC_PUBLIC, ACC_SUPER
Constant pool:
   #1 = Methodref          #5.#21         // java/lang/Object."<init>":()V
   #2 = Fieldref           #22.#23        // java/lang/System.out:Ljava/io/PrintStream;
   #3 = Methodref          #24.#25        // java/io/PrintStream.println:(I)V
   #4 = Class              #26            // com/gaga/byteCode/HelloWordByteCode
   #5 = Class              #27            // java/lang/Object
   #6 = Utf8               <init>
   #7 = Utf8               ()V
   #8 = Utf8               Code
   #9 = Utf8               LineNumberTable
  #10 = Utf8               LocalVariableTable
  #11 = Utf8               this
  #12 = Utf8               Lcom/gaga/byteCode/HelloWordByteCode;
  #13 = Utf8               test1
  #14 = Utf8               i
  #15 = Utf8               I
  #16 = Utf8               test2
  #17 = Utf8               x
  #18 = Utf8               StackMapTable
  #19 = Utf8               SourceFile
  #20 = Utf8               HelloWordByteCode.java
  #21 = NameAndType        #6:#7          // "<init>":()V
  #22 = Class              #28            // java/lang/System
  #23 = NameAndType        #29:#30        // out:Ljava/io/PrintStream;
  #24 = Class              #31            // java/io/PrintStream
  #25 = NameAndType        #32:#33        // println:(I)V
  #26 = Utf8               com/gaga/byteCode/HelloWordByteCode
  #27 = Utf8               java/lang/Object
  #28 = Utf8               java/lang/System
  #29 = Utf8               out
  #30 = Utf8               Ljava/io/PrintStream;
  #31 = Utf8               java/io/PrintStream
  #32 = Utf8               println
  #33 = Utf8               (I)V
{
  public com.gaga.byteCode.HelloWordByteCode();
    descriptor: ()V
    flags: ACC_PUBLIC
    Code:
      stack=1, locals=1, args_size=1
         0: aload_0
         1: invokespecial #1                  // Method java/lang/Object."<init>":()V
         4: return
      LineNumberTable:
        line 8: 0
      LocalVariableTable:
        Start  Length  Slot  Name   Signature
            0       5     0  this   Lcom/gaga/byteCode/HelloWordByteCode;

  public void test1();
    descriptor: ()V
    flags: ACC_PUBLIC
    Code:
      stack=2, locals=2, args_size=1
         0: iconst_0
         1: istore_1
         2: iload_1
         3: iinc          1, 1
         6: istore_1
         7: getstatic     #2                  // Field java/lang/System.out:Ljava/io/PrintStream;
        10: iload_1
        11: invokevirtual #3                  // Method java/io/PrintStream.println:(I)V
        14: return
      LineNumberTable:
        line 15: 0
        line 16: 2
        line 17: 7
        line 18: 14
      LocalVariableTable:
        Start  Length  Slot  Name   Signature
            0      15     0  this   Lcom/gaga/byteCode/HelloWordByteCode;
            2      13     1     i   I

  public void test2();
    descriptor: ()V
    flags: ACC_PUBLIC
    Code:
      stack=2, locals=3, args_size=1
         0: iconst_0
         1: istore_1
         2: iconst_0
         3: istore_2
         4: iload_2
         5: bipush        10
         7: if_icmpge     21
        10: iload_1
        11: iinc          1, 1
        14: istore_1
        15: iinc          2, 1
        18: goto          4
        21: getstatic     #2                  // Field java/lang/System.out:Ljava/io/PrintStream;
        24: iload_1
        25: invokevirtual #3                  // Method java/io/PrintStream.println:(I)V
        28: return
      LineNumberTable:
        line 24: 0
        line 25: 2
        line 26: 10
        line 25: 15
        line 28: 21
        line 29: 28
      LocalVariableTable:
        Start  Length  Slot  Name   Signature
            4      17     2     i   I
            0      29     0  this   Lcom/gaga/byteCode/HelloWordByteCode;
            2      27     1     x   I
      StackMapTable: number_of_entries = 2
        frame_type = 253 /* append */
          offset_delta = 4
          locals = [ int, int ]
        frame_type = 250 /* chop */
          offset_delta = 16
}
SourceFile: "HelloWordByteCode.java"